wordwrap/__init__.py
wordwrap/wordwrap.py
wordwrap-0.2.4.dist-info/licenses/LICENSE
wordwrap-0.2.4.dist-info/METADATA
wordwrap-0.2.4.dist-info/WHEEL
wordwrap-0.2.4.dist-info/top_level.txt
wordwrap-0.2.4.dist-info/RECORD
