Metadata-Version: 2.4
Name: wordwrap
Version: 0.2.4
Summary: A simple library for wrapping text to a fixed column width.
Author: pigmonchu
Maintainer: pigmonchu
License: MIT
Project-URL: Homepage, https://github.com/pigmonchu/wordwrap
Project-URL: Documentation, https://github.com/pigmonchu/wordwrap#readme
Project-URL: Repository, https://github.com/pigmonchu/wordwrap
Project-URL: Bug Tracker, https://github.com/pigmonchu/wordwrap/issues
Project-URL: Changelog, https://github.com/pigmonchu/wordwrap/blob/main/CHANGELOG.md
Keywords: wordwrap,text,wrap,column,formatting,nlp,text-processing
Classifier: Development Status :: 4 - Beta
Classifier: Intended Audience :: Developers
Classifier: License :: OSI Approved :: MIT License
Classifier: Operating System :: OS Independent
Classifier: Programming Language :: Python :: 3
Classifier: Programming Language :: Python :: 3.8
Classifier: Programming Language :: Python :: 3.9
Classifier: Programming Language :: Python :: 3.10
Classifier: Programming Language :: Python :: 3.11
Classifier: Programming Language :: Python :: 3.12
Classifier: Topic :: Software Development :: Libraries :: Python Modules
Classifier: Topic :: Text Processing :: General
Requires-Python: >=3.8
License-File: LICENSE
Provides-Extra: dev
Requires-Dist: pytest>=7.0.0; extra == "dev"
Requires-Dist: pytest-cov>=4.0.0; extra == "dev"
Requires-Dist: black>=22.0.0; extra == "dev"
Requires-Dist: flake8>=4.0.0; extra == "dev"
Requires-Dist: mypy>=1.0.0; extra == "dev"
Requires-Dist: pre-commit>=2.20.0; extra == "dev"
Provides-Extra: docs
Requires-Dist: sphinx>=5.0.0; extra == "docs"
Requires-Dist: sphinx-rtd-theme>=1.0.0; extra == "docs"
Provides-Extra: test
Requires-Dist: pytest>=7.0.0; extra == "test"
Requires-Dist: pytest-cov>=4.0.0; extra == "test"
Requires-Dist: pytest-mock>=3.10.0; extra == "test"
Dynamic: license-file
Dynamic: requires-python
